decotrace
