Metadata-Version: 1.0
Name: decotrace
Version: 0.1.5
Summary: Function/method/class call tracing decorator.
Home-page: https://bitbucket.org/nejucomo/decotrace
Author: Nathan Wilcox
Author-email: nejucomo@gmail.com
License: GPLv3
Platform: UNKNOWN
